ppca/__init__.py
ppca/_ppca.py
ppca-0.0.4.dist-info/LICENSE
ppca-0.0.4.dist-info/METADATA
ppca-0.0.4.dist-info/WHEEL
ppca-0.0.4.dist-info/top_level.txt
ppca-0.0.4.dist-info/RECORD
