Metadata-Version: 1.1
Name: ppca
Version: 0.0.4
Summary: Probabilistic PCA
Home-page: UNKNOWN
Author: Allen Tran
Author-email: realallentran@gmail.com
License: UNKNOWN
Platform: UNKNOWN
Classifier: Development Status :: 4 - Beta
Classifier: Programming Language :: Python
Classifier: Operating System :: Unix
Classifier: Operating System :: MacOS
